personal_jinja/__init__.py
personal_jinja/__main__.py
personal_jinja-0.1.dist-info/LICENSE
personal_jinja-0.1.dist-info/METADATA
personal_jinja-0.1.dist-info/WHEEL
personal_jinja-0.1.dist-info/entry_points.txt
personal_jinja-0.1.dist-info/top_level.txt
personal_jinja-0.1.dist-info/RECORD
